{
  "project_info": {
    "project_number": "225581118834",
    "firebase_url": "https://confrooms-9b2a5.firebaseio.com",
    "project_id": "confrooms-9b2a5",
    "storage_bucket": "confrooms-9b2a5.appspot.com"
  },
  "client": [
    {
      "client_info": {
        "mobilesdk_app_id": "1:225581118834:android:a058eab6c730530a",
        "android_client_info": {
          "package_name": "com.push"
        }
      },
      "oauth_client": [
        {
          "client_id": "225581118834-mequjiua4foj4db3mnhi802jq886jgbl.apps.googleusercontent.com",
          "client_type": 3
        }
      ],
      "api_key": [
        {
          "current_key": "AIzaSyAwL-hGlXTo_trnm3pPeTHEzesd2y1Cbcs"
        }
      ],
      "services": {
        "analytics_service": {
          "status": 1
        },
        "appinvite_service": {
          "status": 1,
          "other_platform_oauth_client": []
        },
        "ads_service": {
          "status": 2
        }
      }
    }
  ],
  "configuration_version": "1"
}